{"cameraMode":{"drawMode":0,"name":"Shaded","section":"Shading Mode"},"sceneLighting":true,"audioPlay":false,"sceneViewState":{"m_AlwaysRefresh":false,"showFog":true,"showSkybox":true,"showFlares":true,"showImageEffects":true,"showParticleSystems":true,"showVisualEffectGraphs":true,"m_FxEnabled":true},"in2DMode":false,"pivot":{"x":609.2701416015625,"y":1474.4437255859375,"z":-279.3927307128906},"rotation":{"x":-0.1923241764307022,"y":-0.10731528699398041,"z":-0.021152528002858163,"w":0.97532719373703},"size":250.0,"orthographic":false}